statistical_tests/__init__.py
statistical_tests/anova.py
statistical_tests/chi_square.py
statistical_tests/t_test.py
statistical_tests/z_test.py
statistical_tests-0.2.1.dist-info/LICENSE
statistical_tests-0.2.1.dist-info/METADATA
statistical_tests-0.2.1.dist-info/WHEEL
statistical_tests-0.2.1.dist-info/top_level.txt
statistical_tests-0.2.1.dist-info/RECORD
