Metadata-Version: 2.1
Name: statistical-tests
Version: 0.2.1
Summary: This Package is an implementation of multiple Statistical Tests e.g. Z-TEST, T-TEST, ANOVA, CHI SQUARE.
Home-page: https://github.com/yourusername/my_project
Author: ABHISHEK MISHRA
Author-email: abhishekmishra0106@gmail.com
License: MIT
Platform: OS Independent
License-File: LICENSE
Requires-Dist: numpy
Requires-Dist: pandas
Requires-Dist: scikit-learn
Requires-Dist: scipy
Requires-Dist: matplotlib
Requires-Dist: seaborn
Requires-Dist: statsmodels
